pyPLNmodels/__init__.py
pyPLNmodels/calculations/_closed_forms.py
pyPLNmodels/calculations/_initialization.py
pyPLNmodels/calculations/elbos.py
pyPLNmodels/calculations/entropies.py
pyPLNmodels/calculations/sandwich.py
pyPLNmodels/load_data/__init__.py
pyPLNmodels/load_data/crossover.py
pyPLNmodels/load_data/microcosm.py
pyPLNmodels/load_data/oaks.py
pyPLNmodels/load_data/scrna.py
pyPLNmodels/load_data/utils.py
pyPLNmodels/load_data/data/crossover/crossover_wide.csv
pyPLNmodels/load_data/data/microcosm/affiliations.tsv
pyPLNmodels/load_data/data/microcosm/counts.tsv
pyPLNmodels/load_data/data/microcosm/metadata.tsv
pyPLNmodels/load_data/data/oaks/counts.csv
pyPLNmodels/load_data/data/oaks/covariates.csv
pyPLNmodels/load_data/data/oaks/offsets.csv
pyPLNmodels/load_data/data/scRT/counts.csv
pyPLNmodels/load_data/data/scRT/labels.csv
pyPLNmodels/models/__init__.py
pyPLNmodels/models/base.py
pyPLNmodels/models/collection.py
pyPLNmodels/models/pln.py
pyPLNmodels/models/plnar.py
pyPLNmodels/models/plndiag.py
pyPLNmodels/models/plnlda.py
pyPLNmodels/models/plnmixture.py
pyPLNmodels/models/plnmixturecollection.py
pyPLNmodels/models/plnnetwork.py
pyPLNmodels/models/plnnetworkcollection.py
pyPLNmodels/models/plnpca.py
pyPLNmodels/models/plnpcacollection.py
pyPLNmodels/models/zipln.py
pyPLNmodels/models/ziplnpca.py
pyPLNmodels/models/ziplnpcacollection.py
pyPLNmodels/sampling/__init__.py
pyPLNmodels/sampling/_base_sampler.py
pyPLNmodels/sampling/_utils.py
pyPLNmodels/sampling/pln_sampling.py
pyPLNmodels/sampling/plnar_sampling.py
pyPLNmodels/sampling/plndiag_sampling.py
pyPLNmodels/sampling/plnlda_sampling.py
pyPLNmodels/sampling/plnmixture_sampling.py
pyPLNmodels/sampling/plnnetwork_sampling.py
pyPLNmodels/sampling/plnpca_sampling.py
pyPLNmodels/sampling/zipln_sampling.py
pyPLNmodels/sampling/ziplnpca_sampling.py
pyPLNmodels/utils/__init__.py
pyPLNmodels/utils/_criterion.py
pyPLNmodels/utils/_data_handler.py
pyPLNmodels/utils/_utils.py
pyPLNmodels/utils/_viz.py
pyplnmodels-1.0.10.dist-info/licenses/LICENSE
pyplnmodels-1.0.10.dist-info/METADATA
pyplnmodels-1.0.10.dist-info/WHEEL
pyplnmodels-1.0.10.dist-info/top_level.txt
pyplnmodels-1.0.10.dist-info/RECORD
