Metadata-Version: 2.4
Name: pyPLNmodels
Version: 1.0.10
Summary: Package implementing PLN models
Author-email: Bastien Batardiere <bastien.batardiere@gmail.com>, Julien Chiquet <julien.chiquet@inrae.fr>, Joon Kwon <joon.kwon@inrae.fr>
Maintainer-email: Bastien Batardière <bastien.batardiere@gmail.com>, Julien Chiquet <julien.chiquet@inrae.fr>
License: MIT License
Project-URL: Repository, https://github.com/PLN-team/pyPLNmodels
Project-URL: Documentation, https://pln-team.github.io/pyPLNmodels/
Project-URL: Tutorials, https://pln-team.github.io/pyPLNmodels/tutorials/
Keywords: python,count,data,count data,high dimension,scRNAseq,PLN
Classifier: Development Status :: 4 - Beta
Classifier: Intended Audience :: Science/Research
Classifier: License :: OSI Approved :: MIT License
Classifier: Programming Language :: Python
Requires-Python: >=3.7
License-File: LICENSE
Requires-Dist: matplotlib
Requires-Dist: numpy
Requires-Dist: pandas
Requires-Dist: scipy
Requires-Dist: seaborn
Requires-Dist: torch
Requires-Dist: scikit-learn
Requires-Dist: patsy
Requires-Dist: tqdm
Requires-Dist: networkx
Provides-Extra: tests
Requires-Dist: pytest; extra == "tests"
Requires-Dist: pytest-cov; extra == "tests"
Provides-Extra: build-doc
Requires-Dist: sphinx; extra == "build-doc"
Requires-Dist: sphinx_rtd_theme; extra == "build-doc"
Requires-Dist: sphinx_copybutton; extra == "build-doc"
Requires-Dist: sphinx_codeautolink; extra == "build-doc"
Requires-Dist: autoclasstoc; extra == "build-doc"
Requires-Dist: jupyter-cache; extra == "build-doc"
Dynamic: license-file
